{
  "basic": [
    { "id": "anti-slow", "cost": 500, "appliesTo": ["weapon", "armor", "shield", "accessory"] },
    { "id": "anti-daze", "cost": 500, "appliesTo": ["weapon", "armor", "shield", "accessory"] },
    { "id": "anti-shaken", "cost": 500, "appliesTo": ["weapon", "armor", "shield", "accessory"] },
    { "id": "anti-weak", "cost": 500, "appliesTo": ["weapon", "armor", "shield", "accessory"] },
    { "id": "anti-poison", "cost": 500, "appliesTo": ["weapon", "armor", "shield", "accessory"] },
    { "id": "anti-enrage", "cost": 500, "appliesTo": ["weapon", "armor", "shield", "accessory"] },

    { "id": "resist-fire", "cost": 700, "appliesTo": ["weapon", "armor", "shield", "accessory"] },
    { "id": "resist-earth", "cost": 700, "appliesTo": ["weapon", "armor", "shield", "accessory"] },
    { "id": "resist-ice", "cost": 700, "appliesTo": ["weapon", "armor", "shield", "accessory"] },
    { "id": "resist-air", "cost": 700, "appliesTo": ["weapon", "armor", "shield", "accessory"] },
    { "id": "resist-bolt", "cost": 700, "appliesTo": ["weapon", "armor", "shield", "accessory"] },
    { "id": "resist-dark", "cost": 700, "appliesTo": ["weapon", "armor", "shield", "accessory"] },
    { "id": "resist-light", "cost": 700, "appliesTo": ["weapon", "armor", "shield", "accessory"] },
    { "id": "resist-poison", "cost": 700, "appliesTo": ["weapon", "armor", "shield", "accessory"] },

    { "id": "resist-fire-earth", "cost": 1000, "appliesTo": ["weapon", "armor", "shield", "accessory"] },
    { "id": "resist-fire-ice", "cost": 1000, "appliesTo": ["weapon", "armor", "shield", "accessory"] },
    { "id": "resist-fire-air", "cost": 1000, "appliesTo": ["weapon", "armor", "shield", "accessory"] },
    { "id": "resist-fire-bolt", "cost": 1000, "appliesTo": ["weapon", "armor", "shield", "accessory"] },
    { "id": "resist-fire-dark", "cost": 1000, "appliesTo": ["weapon", "armor", "shield", "accessory"] },
    { "id": "resist-fire-light", "cost": 1000, "appliesTo": ["weapon", "armor", "shield", "accessory"] },
    { "id": "resist-fire-poison", "cost": 1000, "appliesTo": ["weapon", "armor", "shield", "accessory"] },

    { "id": "resist-earth-ice", "cost": 1000, "appliesTo": ["weapon", "armor", "shield", "accessory"] },
    { "id": "resist-earth-air", "cost": 1000, "appliesTo": ["weapon", "armor", "shield", "accessory"] },
    { "id": "resist-earth-bolt", "cost": 1000, "appliesTo": ["weapon", "armor", "shield", "accessory"] },
    { "id": "resist-earth-dark", "cost": 1000, "appliesTo": ["weapon", "armor", "shield", "accessory"] },
    { "id": "resist-earth-light", "cost": 1000, "appliesTo": ["weapon", "armor", "shield", "accessory"] },
    { "id": "resist-earth-poison", "cost": 1000, "appliesTo": ["weapon", "armor", "shield", "accessory"] },

    { "id": "resist-ice-air", "cost": 1000, "appliesTo": ["weapon", "armor", "shield", "accessory"] },
    { "id": "resist-ice-bolt", "cost": 1000, "appliesTo": ["weapon", "armor", "shield", "accessory"] },
    { "id": "resist-ice-dark", "cost": 1000, "appliesTo": ["weapon", "armor", "shield", "accessory"] },
    { "id": "resist-ice-light", "cost": 1000, "appliesTo": ["weapon", "armor", "shield", "accessory"] },
    { "id": "resist-ice-poison", "cost": 1000, "appliesTo": ["weapon", "armor", "shield", "accessory"] },

    { "id": "resist-air-bolt", "cost": 1000, "appliesTo": ["weapon", "armor", "shield", "accessory"] },
    { "id": "resist-air-dark", "cost": 1000, "appliesTo": ["weapon", "armor", "shield", "accessory"] },
    { "id": "resist-air-light", "cost": 1000, "appliesTo": ["weapon", "armor", "shield", "accessory"] },
    { "id": "resist-air-poison", "cost": 1000, "appliesTo": ["weapon", "armor", "shield", "accessory"] },

    { "id": "resist-bolt-dark", "cost": 1000, "appliesTo": ["weapon", "armor", "shield", "accessory"] },
    { "id": "resist-bolt-light", "cost": 1000, "appliesTo": ["weapon", "armor", "shield", "accessory"] },
    { "id": "resist-bolt-poison", "cost": 1000, "appliesTo": ["weapon", "armor", "shield", "accessory"] },

    { "id": "resist-dark-light", "cost": 1000, "appliesTo": ["weapon", "armor", "shield", "accessory"] },
    { "id": "resist-dark-poison", "cost": 1000, "appliesTo": ["weapon", "armor", "shield", "accessory"] },
    { "id": "resist-light-poison", "cost": 1000, "appliesTo": ["weapon", "armor", "shield", "accessory"] },

    { "id": "swordbreaker", "cost": 1000, "appliesTo": ["weapon", "armor", "shield", "accessory"] },

    { "id": "fire-immunity", "cost": 1500, "appliesTo": ["weapon", "armor", "shield", "accessory"] },
    { "id": "earth-immunity", "cost": 1500, "appliesTo": ["weapon", "armor", "shield", "accessory"] },
    { "id": "ice-immunity", "cost": 1500, "appliesTo": ["weapon", "armor", "shield", "accessory"] },
    { "id": "air-immunity", "cost": 1500, "appliesTo": ["weapon", "armor", "shield", "accessory"] },
    { "id": "bolt-immunity", "cost": 1500, "appliesTo": ["weapon", "armor", "shield", "accessory"] },
    { "id": "dark-immunity", "cost": 1500, "appliesTo": ["weapon", "armor", "shield", "accessory"] },
    { "id": "light-immunity", "cost": 1500, "appliesTo": ["weapon", "armor", "shield", "accessory"] },
    { "id": "poison-immunity", "cost": 1500, "appliesTo": ["weapon", "armor", "shield", "accessory"] },

    { "id": "omnishield", "cost": 2000, "appliesTo": ["weapon", "armor", "shield", "accessory"] },
    { "id": "perfect-health", "cost": 2000, "appliesTo": ["weapon", "armor", "shield", "accessory"] },

    { "id": "magical", "cost": 100, "appliesTo": ["weapon"] },
    { "id": "beast-hunter", "cost": 300, "appliesTo": ["weapon"] },
    { "id": "construct-hunter", "cost": 300, "appliesTo": ["weapon"] },
    { "id": "demon-hunter", "cost": 300, "appliesTo": ["weapon"] },
    { "id": "elemental-hunter", "cost": 300, "appliesTo": ["weapon"] },
    { "id": "monster-hunter", "cost": 300, "appliesTo": ["weapon"] },
    { "id": "plant-hunter", "cost": 300, "appliesTo": ["weapon"] },
    { "id": "undead-hunter", "cost": 300, "appliesTo": ["weapon"] },
    { "id": "human-hunter", "cost": 300, "appliesTo": ["weapon"] },
    { "id": "piercing", "cost": 400, "appliesTo": ["weapon"] },

    { "id": "hunter-beasts-constructs", "cost": 500, "appliesTo": ["weapon"] },
    { "id": "hunter-beasts-demons", "cost": 500, "appliesTo": ["weapon"] },
    { "id": "hunter-beasts-elementals", "cost": 500, "appliesTo": ["weapon"] },
    { "id": "hunter-beasts-humanoids", "cost": 500, "appliesTo": ["weapon"] },
    { "id": "hunter-beasts-monsters", "cost": 500, "appliesTo": ["weapon"] },
    { "id": "hunter-beasts-plants", "cost": 500, "appliesTo": ["weapon"] },
    { "id": "hunter-beasts-undead", "cost": 500, "appliesTo": ["weapon"] },
    { "id": "hunter-constructs-demons", "cost": 500, "appliesTo": ["weapon"] },
    { "id": "hunter-constructs-elementals", "cost": 500, "appliesTo": ["weapon"] },
    { "id": "hunter-constructs-humanoids", "cost": 500, "appliesTo": ["weapon"] },
    { "id": "hunter-constructs-monsters", "cost": 500, "appliesTo": ["weapon"] },
    { "id": "hunter-constructs-plants", "cost": 500, "appliesTo": ["weapon"] },
    { "id": "hunter-constructs-undead", "cost": 500, "appliesTo": ["weapon"] },
    { "id": "hunter-demons-elementals", "cost": 500, "appliesTo": ["weapon"] },
    { "id": "hunter-demons-humanoids", "cost": 500, "appliesTo": ["weapon"] },
    { "id": "hunter-demons-monsters", "cost": 500, "appliesTo": ["weapon"] },
    { "id": "hunter-demons-plants", "cost": 500, "appliesTo": ["weapon"] },
    { "id": "hunter-demons-undead", "cost": 500, "appliesTo": ["weapon"] },
    { "id": "hunter-elementals-humanoids", "cost": 500, "appliesTo": ["weapon"] },
    { "id": "hunter-elementals-monsters", "cost": 500, "appliesTo": ["weapon"] },
    { "id": "hunter-elementals-plants", "cost": 500, "appliesTo": ["weapon"] },
    { "id": "hunter-elementals-undead", "cost": 500, "appliesTo": ["weapon"] },
    { "id": "hunter-humanoids-monsters", "cost": 500, "appliesTo": ["weapon"] },
    { "id": "hunter-humanoids-plants", "cost": 500, "appliesTo": ["weapon"] },
    { "id": "hunter-humanoids-undead", "cost": 500, "appliesTo": ["weapon"] },
    { "id": "hunter-monsters-plants", "cost": 500, "appliesTo": ["weapon"] },
    { "id": "hunter-monsters-undead", "cost": 500, "appliesTo": ["weapon"] },
    { "id": "hunter-plants-undead", "cost": 500, "appliesTo": ["weapon"] },

    { "id": "multi", "cost": 1000, "appliesTo": ["weapon"] },
    { "id": "inflict-slow", "cost": 1500, "appliesTo": ["weapon"] },
    { "id": "inflict-daze", "cost": 1500, "appliesTo": ["weapon"] },
    { "id": "inflict-shaken", "cost": 1500, "appliesTo": ["weapon"] },
    { "id": "inflict-weak", "cost": 1500, "appliesTo": ["weapon"] },
    { "id": "inflict-poison", "cost": 2000, "appliesTo": ["weapon"] },
    { "id": "inflict-enrage", "cost": 2000, "appliesTo": ["weapon"] },

    { "id": "initiative-up", "cost": 500, "appliesTo": ["armor", "shield", "accessory"] },
    { "id": "accuracy-up", "cost": 1000, "appliesTo": ["armor", "shield", "accessory"] },
    { "id": "magic-up", "cost": 1000, "appliesTo": ["armor", "shield", "accessory"] },
    { "id": "vitality-up", "cost": 1000, "appliesTo": ["armor", "shield", "accessory"] },
    { "id": "healing-up", "cost": 1500, "appliesTo": ["armor", "shield", "accessory"] },
    { "id": "spell-up", "cost": 2000, "appliesTo": ["armor", "shield", "accessory"] },
    { "id": "melee-up", "cost": 2000, "appliesTo": ["armor", "shield", "accessory"] },
    { "id": "ranged-up", "cost": 2000, "appliesTo": ["armor", "shield", "accessory"] },

    { "id": "amulet", "cost": 800, "appliesTo": ["weapon", "accessory"] },
    { "id": "bulwark", "cost": 800, "appliesTo": ["weapon", "accessory"] }
  ],

  "aerial": [
    { "id": "aerial-1", "cost": 600, "appliesTo": ["weapon", "armor", "shield", "accessory"] },
    { "id": "aerial-2", "cost": 600, "appliesTo": ["weapon"] },
    { "id": "aerial-3", "cost": 800, "appliesTo": ["weapon"] },
    { "id": "aerial-4", "cost": 900, "appliesTo": ["weapon", "armor", "shield", "accessory"] },
    { "id": "aerial-5", "cost": 1000, "appliesTo": ["weapon", "armor", "shield", "accessory"] },
    { "id": "aerial-6", "cost": 1200, "appliesTo": ["weapon", "armor", "shield", "accessory"] }
  ],

  "thunderous": [
    { "id": "thunderous-1", "cost": 600, "appliesTo": ["weapon", "armor", "shield", "accessory"] },
    { "id": "thunderous-2", "cost": 800, "appliesTo": ["weapon"] },
    { "id": "thunderous-3", "cost": 1000, "appliesTo": ["weapon", "armor", "shield", "accessory"] },
    { "id": "thunderous-4", "cost": 1000, "appliesTo": ["weapon", "armor", "shield", "accessory"] },
    { "id": "thunderous-5", "cost": 1200, "appliesTo": ["weapon", "armor", "shield", "accessory"] },
    { "id": "thunderous-6", "cost": 1500, "appliesTo": ["weapon"] }
  ],

  "paradox": [
    { "id": "paradox-1", "cost": 600, "appliesTo": ["weapon"] },
    { "id": "paradox-2", "cost": 800, "appliesTo": ["weapon", "armor", "shield", "accessory"] },
    { "id": "paradox-3", "cost": 1000, "appliesTo": ["weapon"] },
    { "id": "paradox-4", "cost": 1200, "appliesTo": ["weapon", "armor", "shield", "accessory"] },
    { "id": "paradox-5", "cost": 1500, "appliesTo": ["weapon", "armor", "shield", "accessory"] },
    { "id": "paradox-6", "cost": 1800, "appliesTo": ["weapon"] }
  ],

  "terrestrial": [
    { "id": "terrestrial-1", "cost": 600, "appliesTo": ["weapon", "armor", "shield", "accessory"] },
    { "id": "terrestrial-2", "cost": 800, "appliesTo": ["weapon", "armor", "shield", "accessory"] },
    { "id": "terrestrial-3", "cost": 1000, "appliesTo": ["weapon"] },
    { "id": "terrestrial-4", "cost": 1000, "appliesTo": ["weapon", "armor", "shield", "accessory"] },
    { "id": "terrestrial-5", "cost": 1500, "appliesTo": ["weapon", "armor", "shield", "accessory"] },
    { "id": "terrestrial-6", "cost": 1800, "appliesTo": ["weapon", "armor", "shield", "accessory"] }
  ],

  "ardent": [
    { "id": "ardent-1", "cost": 500, "appliesTo": ["weapon", "armor", "shield", "accessory"] },
    { "id": "ardent-2", "cost": 600, "appliesTo": ["weapon"] },
    { "id": "ardent-3", "cost": 600, "appliesTo": ["weapon"] },
    { "id": "ardent-4", "cost": 800, "appliesTo": ["weapon", "armor", "shield", "accessory"] },
    { "id": "ardent-5", "cost": 1300, "appliesTo": ["weapon"] },
    { "id": "ardent-6", "cost": 1800, "appliesTo": ["weapon", "armor", "shield", "accessory"] }
  ],

  "glacial": [
    { "id": "glacial-1", "cost": 600, "appliesTo": ["weapon", "armor", "shield", "accessory"] },
    { "id": "glacial-2", "cost": 800, "appliesTo": ["weapon", "armor", "shield", "accessory"] },
    { "id": "glacial-3", "cost": 1000, "appliesTo": ["weapon", "armor", "shield", "accessory"] },
    { "id": "glacial-4", "cost": 1000, "appliesTo": ["weapon", "armor", "shield", "accessory"] },
    { "id": "glacial-5", "cost": 1800, "appliesTo": ["weapon", "armor", "shield", "accessory"] },
    { "id": "glacial-6", "cost": 1800, "appliesTo": ["weapon", "armor", "shield", "accessory"] }
  ],

  "spiritual": [
    { "id": "spiritual-1", "cost": 600, "appliesTo": ["weapon", "armor", "shield", "accessory"] },
    { "id": "spiritual-2", "cost": 800, "appliesTo": ["weapon"] },
    { "id": "spiritual-3", "cost": 1000, "appliesTo": ["weapon", "armor", "shield", "accessory"] },
    { "id": "spiritual-4", "cost": 1000, "appliesTo": ["weapon"] },
    { "id": "spiritual-5", "cost": 1000, "appliesTo": ["weapon", "armor", "shield", "accessory"] },
    { "id": "spiritual-6", "cost": 1500, "appliesTo": ["weapon", "armor", "shield", "accessory"] }
  ],

  "corrupted": [
    { "id": "corrupted-1", "cost": 600, "appliesTo": ["weapon"] },
    { "id": "corrupted-2", "cost": 1000, "appliesTo": ["weapon", "armor", "shield", "accessory"] },
    { "id": "corrupted-3", "cost": 1000, "appliesTo": ["weapon", "armor", "shield", "accessory"] },
    { "id": "corrupted-4", "cost": 1000, "appliesTo": ["weapon", "armor", "shield", "accessory"] },
    { "id": "corrupted-5", "cost": 1200, "appliesTo": ["weapon", "armor", "shield", "accessory"] },
    { "id": "corrupted-6", "cost": 1500, "appliesTo": ["weapon"] }
  ],

  "aquatic": [
    { "id": "aquatic-1", "cost": 600, "appliesTo": ["weapon", "armor", "shield", "accessory"] },
    { "id": "aquatic-2", "cost": 800, "appliesTo": ["weapon"] },
    { "id": "aquatic-3", "cost": 1000, "appliesTo": ["weapon", "armor", "shield", "accessory"] },
    { "id": "aquatic-4", "cost": 1000, "appliesTo": ["weapon"] },
    { "id": "aquatic-5", "cost": 1200, "appliesTo": ["weapon", "armor", "shield", "accessory"] },
    { "id": "aquatic-6", "cost": 1500, "appliesTo": ["weapon"] }
  ],

  "mechanical": [
    { "id": "mechanical-1", "cost": 300, "appliesTo": ["weapon", "armor", "shield", "accessory"] },
    { "id": "mechanical-2", "cost": 600, "appliesTo": ["weapon"] },
    { "id": "mechanical-3", "cost": 800, "appliesTo": ["weapon", "armor", "shield", "accessory"] },
    { "id": "mechanical-4", "cost": 1000, "appliesTo": ["weapon"] },
    { "id": "mechanical-5", "cost": 1200, "appliesTo": ["weapon", "armor", "shield", "accessory"] },
    { "id": "mechanical-6", "cost": 1500, "appliesTo": ["weapon", "armor", "shield", "accessory"] }
  ]
}
